printlogr/__init__.py
printlogr/cli.py
printlogr/print_logger.py
printlogr-0.3.1.dist-info/licenses/LICENSE
printlogr-0.3.1.dist-info/METADATA
printlogr-0.3.1.dist-info/WHEEL
printlogr-0.3.1.dist-info/entry_points.txt
printlogr-0.3.1.dist-info/top_level.txt
printlogr-0.3.1.dist-info/RECORD
