Metadata-Version: 2.4
Name: printlogr
Version: 0.3.1
Summary: A Python library for logging and PDF report generation
Home-page: https://github.com/inderrana/printlogr
Author: Inder Rana
License: MIT
Project-URL: Homepage, https://github.com/inderrana/printlogr
Project-URL: Bug Tracker, https://github.com/inderrana/printlogr/issues
Keywords: logging,print,timestamp,pdf,csv,txt
Classifier: Programming Language :: Python :: 3
Classifier: Operating System :: OS Independent
Classifier: Development Status :: 3 - Alpha
Classifier: Intended Audience :: Developers
Classifier: Topic :: Software Development :: Libraries :: Python Modules
Classifier: Topic :: System :: Logging
Classifier: Topic :: Text Processing :: Markup
Requires-Python: >=3.7
License-File: LICENSE
Requires-Dist: reportlab>=4.0.0
Provides-Extra: dev
Requires-Dist: pytest>=7.0.0; extra == "dev"
Requires-Dist: pytest-cov>=4.0.0; extra == "dev"
Requires-Dist: black>=22.0.0; extra == "dev"
Requires-Dist: isort>=5.0.0; extra == "dev"
Requires-Dist: flake8>=4.0.0; extra == "dev"
Requires-Dist: twine>=4.0.0; extra == "dev"
Requires-Dist: build>=1.0.0; extra == "dev"
Dynamic: home-page
Dynamic: license-file
Dynamic: requires-python
